spi.v
module spi(sclk, sdio, sen,reset);

input sclk; // sclk clock by master
inout sdio; // input output line
input sen; //line which lows when tranction is started
input reset; // reset when high
reg sdio_reg_s=1'b0; //refers sdio register of slave which is used while transfering data from slave to master
reg [2:0]data_count_r=3'b000; // for counting reading data
reg [7:0] memory[4095:0]; //memory array declaration
reg [7:0] data=8'b0;       //register to store 8 bit data
reg [11:0] address=12'b0;  //register to store 12 bit address
reg [23:0] bit_24_reg =24'b0; //regiter to store whole transaction
reg [4:0] bit_counter =5'b0; //counter for counting bits
reg [2:0] data_count_w=3'b0; //for counting no. of bits of writing data
reg [3:0] address_count=4'b0; // for counting no. of bits of address
reg read_write_bit=1'b0; // to decide which operation to perform

parameter NO=2'b00, READ=2'b01, WRITE=2'b10;
reg [1:0] state=NO;

assign sdio = (read_write_bit) ? sdio_reg_s : 1'hz;

always@(posedge sclk or posedge reset or posedge sen) begin

 // reset block for reseting signals when reset is high
 if(reset)begin
 data<=8'b0;
 address<=12'b0;
 bit_24_reg<=24'b0;
 bit_counter<=5'b0;
 data_count_w<=3'b0;
 address_count<=4'b0;
 read_write_bit<=1'b0;
 state<=2'b00;
 end
 
 
 
 // block what to do when sen is 0
 if(!sen) begin
  bit_counter <= bit_counter + 5'b00001;
  bit_24_reg[23-bit_counter] <= sdio;
 
 
 //if block for storing address
  if((bit_counter>5'b00011) && (bit_counter<5'b10000)) begin
  address_count <= address_count + 4'b0001;
  address[11-address_count] <= sdio;
  end
  
  
 //if block to judge whether to read or write
  if (bit_counter == 5'b01111) begin
    if (bit_24_reg[23]) begin //if bit is high then read else write
        state <= READ;
        read_write_bit <= 1'b1;
    end
    else begin
        state <= WRITE;
        read_write_bit <= 1'b0;
    end
  end
  
  
 //if block to write data when masters writes
  if((bit_counter>5'b01111) && (bit_counter<5'b11000)) begin
  case(state) 
  
  WRITE : begin
  
  data_count_w <= data_count_w + 3'b001;
  memory[address][7-data_count_w] <= sdio;
  end
  
  endcase
  end
  
  
 end
 // block when what to do sen is 0 and reset is 0
 else begin 
 data<=8'b0;
 address<=12'b0;
 bit_24_reg<=24'b0;
 bit_counter<=5'b0;
 data_count_w<=3'b0;
 address_count<=4'b0;
 read_write_bit<=1'b0;
 state<=2'b00;
 data_count_w<=3'b0;
 end 
end

always@(negedge sclk or posedge reset or posedge sen) begin

// reset block for reseting signals when reset is high
if(reset)begin
data_count_r<=3'b0;
end

        // block what to do when sen is 0
	if(!sen) begin
	
	//if block to transfer data when master reads
	if((bit_counter>5'b01111) && (bit_counter<5'b11000)) begin
	
	case (state)
	
		READ : begin
  
		data_count_r <= data_count_r + 3'b001;
		sdio_reg_s <= memory[address][7-data_count_r] ;
  
		end
		
	endcase
	
	end
	end
	// block when what to do sen is 0 and reset is 0
	else begin
	data_count_r<=3'b0;
	end
	
end
endmodule

read_tb.v
module spi_tb();
reg sclk; // clock line given by master
wire sdio; // bidirectional transaction line
reg sdio_reg_m; // register used to transfer data from MASTER to SLAVE
reg sen; // transaction enable line
reg reset; // reset pin
reg decide=1'b0; // this variable is used to decide whether sdio will work as input or output line
reg [7:0]data_store=8'b0; // this register stores data coming from SLAVE in MASTER
integer i,j; // variables for running loop
reg [15:0] in = 16'b1000101000001101; //input register which contains all the bits that are to be sent
spi S1(.sclk(sclk),.sdio(sdio),.sen(sen),.reset(reset)); // declaration of spi module

assign sdio = (decide)? 1'hz : sdio_reg_m ; //line to control whether the sdio will act as input or output

initial begin
S1.memory[2573] = 8'b10110011; //storing of data at memory location so we can fetch in read operation from SLAVE
 sen=1'b1;
 sclk=1'b1;

 forever #50 sclk = ~sclk; //clock period of 100
 end
 
 
initial begin
 reset=1'b0;
 #50
 reset=1'b1;
 #40
 reset=1'b0;
 #110
 sen=1'b0;
 for(i=0;i<16;i=i+1) begin // for loop to send 16 bits sequentially containing read or write bit + 3 bits and other 12 bits of address
 if(i<15) begin //for srnding first 15 bits as it is
 sdio_reg_m=in[15-i];

 #100;
 end
 else begin  // at 16 bit sdio will change from input to SLAVE to output from SLAVE
 sdio_reg_m=in[15-i];
 #1 //this delay is give so as to store last bit address and then change mode of sdio line
 decide=1'b1;
 #50;
 end
 
end
 
 #50; // wait for posedge to capture sent by SLAVE on previous negedge
 
for(j=0;j<8;j=j+1) begin //for loop to recieve data from SLAVE
    data_store[7-j] = sdio;
    #100;
end

 sen=1'b1; // making sen high to disable transaction after successful transfer
 #100
 $finish;
end

// printing signals for monitoring
initial begin
    $monitor("Time=%0t | sclk=%b sdio=%b sen=%b  reset=%b state=%b address=%b bit_counter=%b  data_count=%b sdio_reg =%b, data=%b bits=%b",
              $time, sclk, sdio, sen, reset, S1.state, S1.address, S1.bit_counter,S1.data_count_r,S1.sdio_reg_s,data_store,S1.bit_24_reg);
              $display("mem =%b",S1.memory[2573]);
end

// dumping of data in file
initial begin
 $dumpfile("read.vcd"); // specifies the VCD file
 $dumpvars(0, spi_tb); //dump all the variables
end


endmodule

read.vcd
$date
	Fri Jun 12 16:30:58 2026
$end
$version
	Icarus Verilog
$end
$timescale
	1s
$end
$scope module spi_tb $end
$var wire 1 ! sdio $end
$var reg 8 " data_store [7:0] $end
$var reg 1 # decide $end
$var reg 16 $ in [15:0] $end
$var reg 1 % reset $end
$var reg 1 & sclk $end
$var reg 1 ' sdio_reg_m $end
$var reg 1 ( sen $end
$var integer 32 ) i [31:0] $end
$var integer 32 * j [31:0] $end
$scope module S1 $end
$var wire 1 % reset $end
$var wire 1 & sclk $end
$var wire 1 ! sdio $end
$var wire 1 ( sen $end
$var parameter 2 + NO $end
$var parameter 2 , READ $end
$var parameter 2 - WRITE $end
$var reg 12 . address [11:0] $end
$var reg 4 / address_count [3:0] $end
$var reg 24 0 bit_24_reg [23:0] $end
$var reg 5 1 bit_counter [4:0] $end
$var reg 8 2 data [7:0] $end
$var reg 3 3 data_count_r [2:0] $end
$var reg 3 4 data_count_w [2:0] $end
$var reg 1 5 read_write_bit $end
$var reg 1 6 sdio_reg_s $end
$var reg 2 7 state [1:0] $end
$upscope $end
$upscope $end
$enddefinitions $end
$comment Show the parameter values. $end
$dumpall
b10 -
b1 ,
b0 +
$end
#0
$dumpvars
b0 7
06
05
b0 4
b0 3
b0 2
b0 1
b0 0
b0 /
b0 .
bx *
bx )
1(
x'
1&
0%
b1000101000001101 $
0#
b0 "
x!
$end
#50
1%
0&
#90
0%
#100
1&
#150
0&
#200
b100000000000000000000000 0
b1 1
1!
1&
1'
b0 )
0(
#250
0&
#300
b10 1
0!
1&
0'
b1 )
#350
0&
#400
b11 1
1&
b10 )
#450
0&
#500
b100 1
1&
b11 )
#550
0&
#600
b100000000000 .
b1 /
b100010000000000000000000 0
b101 1
1!
1&
1'
b100 )
#650
0&
#700
b10 /
b110 1
0!
1&
0'
b101 )
#750
0&
#800
b101000000000 .
b11 /
b100010100000000000000000 0
b111 1
1!
1&
1'
b110 )
#850
0&
#900
b100 /
b1000 1
0!
1&
0'
b111 )
#950
0&
#1000
b101 /
b1001 1
1&
b1000 )
#1050
0&
#1100
b110 /
b1010 1
1&
b1001 )
#1150
0&
#1200
b111 /
b1011 1
1&
b1010 )
#1250
0&
#1300
b1000 /
b1100 1
1&
b1011 )
#1350
0&
#1400
b101000001000 .
b1001 /
b100010100000100000000000 0
b1101 1
1!
1&
1'
b1100 )
#1450
0&
#1500
b101000001100 .
b1010 /
b100010100000110000000000 0
b1110 1
1&
b1101 )
#1550
0&
#1600
b1011 /
b1111 1
0!
1&
0'
b1110 )
#1650
0&
#1700
15
b1 7
b101000001101 .
b1100 /
b100010100000110100000000 0
b10000 1
x!
1&
1'
b1111 )
#1701
0!
1#
#1750
1!
16
b1 3
0&
#1751
b10000 )
#1800
b100010100000110110000000 0
b10001 1
1&
#1801
b10000000 "
b0 *
#1850
0!
06
b10 3
0&
#1900
b10010 1
1&
#1901
b1 *
#1950
1!
16
b11 3
0&
#2000
b100010100000110110100000 0
b10011 1
1&
#2001
b10100000 "
b10 *
#2050
b100 3
0&
#2100
b100010100000110110110000 0
b10100 1
1&
#2101
b10110000 "
b11 *
#2150
0!
06
b101 3
0&
#2200
b10101 1
1&
#2201
b100 *
#2250
b110 3
0&
#2300
b10110 1
1&
#2301
b101 *
#2350
1!
16
b111 3
0&
#2400
b100010100000110110110010 0
b10111 1
1&
#2401
b10110010 "
b110 *
#2450
b0 3
0&
#2500
b100010100000110110110011 0
b11000 1
1&
#2501
b10110011 "
b111 *
#2550
0&
#2600
b11001 1
1&
#2601
z!
b0 7
05
b0 /
b0 1
b0 0
b0 .
1(
b1000 *
