spi.v
module spi(sclk, sdio, sen,reset);

input sclk; // sclk clock by master
inout sdio; // input output line
input sen; //line which lows when tranction is started
input reset; // reset when high
reg sdio_reg_s=1'b0; //refers sdio register of slave which is used while transfering data from slave to master
reg [2:0]data_count_r=3'b000; // for counting reading data
reg [7:0] memory[4095:0]; //memory array declaration
reg [7:0] data=8'b0;       //register to store 8 bit data
reg [11:0] address=12'b0;  //register to store 12 bit address
reg [23:0] bit_24_reg =24'b0; //regiter to store whole transaction
reg [4:0] bit_counter =5'b0; //counter for counting bits
reg [2:0] data_count_w=3'b0; //for counting no. of bits of writing data
reg [3:0] address_count=4'b0; // for counting no. of bits of address
reg read_write_bit=1'b0; // to decide which operation to perform

parameter NO=2'b00, READ=2'b01, WRITE=2'b10;
reg [1:0] state=NO;

assign sdio = (read_write_bit) ? sdio_reg_s : 1'hz;

always@(posedge sclk or posedge reset or posedge sen) begin

 // reset block for reseting signals when reset is high
 if(reset)begin
 data<=8'b0;
 address<=12'b0;
 bit_24_reg<=24'b0;
 bit_counter<=5'b0;
 data_count_w<=3'b0;
 address_count<=4'b0;
 read_write_bit<=1'b0;
 state<=2'b00;
 end
 
 
 
 // block what to do when sen is 0
 if(!sen) begin
  bit_counter <= bit_counter + 5'b00001;
  bit_24_reg[23-bit_counter] <= sdio;
 
 
 //if block for storing address
  if((bit_counter>5'b00011) && (bit_counter<5'b10000)) begin
  address_count <= address_count + 4'b0001;
  address[11-address_count] <= sdio;
  end
  
  
 //if block to judge whether to read or write
  if (bit_counter == 5'b01111) begin
    if (bit_24_reg[23]) begin //if bit is high then read else write
        state <= READ;
        read_write_bit <= 1'b1;
    end
    else begin
        state <= WRITE;
        read_write_bit <= 1'b0;
    end
  end
  
  
 //if block to write data when masters writes
  if((bit_counter>5'b01111) && (bit_counter<5'b11000)) begin
  case(state) 
  
  WRITE : begin
  
  data_count_w <= data_count_w + 3'b001;
  memory[address][7-data_count_w] <= sdio;
  end
  
  endcase
  end
  
  
 end
 // block when what to do sen is 0 and reset is 0
 else begin 
 data<=8'b0;
 address<=12'b0;
 bit_24_reg<=24'b0;
 bit_counter<=5'b0;
 data_count_w<=3'b0;
 address_count<=4'b0;
 read_write_bit<=1'b0;
 state<=2'b00;
 data_count_w<=3'b0;
 end 
end

always@(negedge sclk or posedge reset or posedge sen) begin

// reset block for reseting signals when reset is high
if(reset)begin
data_count_r<=3'b0;
end

        // block what to do when sen is 0
	if(!sen) begin
	
	//if block to transfer data when master reads
	if((bit_counter>5'b01111) && (bit_counter<5'b11000)) begin
	
	case (state)
	
		READ : begin
  
		data_count_r <= data_count_r + 3'b001;
		sdio_reg_s <= memory[address][7-data_count_r] ;
  
		end
		
	endcase
	
	end
	end
	// block when what to do sen is 0 and reset is 0
	else begin
	data_count_r<=3'b0;
	end
	
end
endmodule

write_tb.v
module spi_tb();
reg sclk;  // clock line given by master
wire sdio; // bidirectional transaction line
reg sdio_reg_m; // register used to transfer data from MASTER to SLAVE
reg sen; // transaction enable line
reg reset; // reset pin
reg decide=1'b0; // this variable is used to decide whether sdio will work as input or output line
reg [7:0]data_store=8'b0; // this register stores data coming from SLAVE in MASTER
integer i=0; // variable for running loop
reg [23:0] in = 24'b000010100000110110001100; //input register which contains all the bits that are to be sent
spi S1(.sclk(sclk),.sdio(sdio),.sen(sen),.reset(reset)); // declaration of spi module 

assign sdio = (!decide)? sdio_reg_m : 1'hz; //line to control whether the sdio will act as input or output

initial begin
 sen=1'b1;
 sclk=1'b1;
 
 forever #50 sclk = ~sclk; //clock period of 100 time units
 end
 
initial begin
reset=1'b0;
#50
reset=1'b1;
#40
reset=1'b0;
#110
sen=1'b0; // lowering the sen line to enable the transaction


for(i=0;i<24;i=i+1) begin // for loop to send 24 bits sequentially
 sdio_reg_m=in[23-i]; //23-i for sending MSB first
 #100;
 end
 
 sen=1'b1; // making sen high to disable transaction after successful transfer
 #100
 $finish;
 
end

// printing signals for monitoring
initial begin
   $monitor("Time=%0t | sclk=%b sdio=%b sen=%b  reset=%b data=%b address=%b bit_counter=%b bits=%b data_b=%b mem = %b",
              $time, sclk, sdio, sen, reset, S1.data, S1.address, S1.bit_counter,S1.bit_24_reg,S1.data_count_w, S1.memory[2573]);
end

// dumping of data in file
initial begin
 $dumpfile("write.vcd"); // specifies the VCD file
 $dumpvars(0, spi_tb); //dump all the variables
end

endmodule

write.vcd
$date
	Fri Jun 12 16:30:26 2026
$end
$version
	Icarus Verilog
$end
$timescale
	1s
$end
$scope module spi_tb $end
$var wire 1 ! sdio $end
$var reg 8 " data_store [7:0] $end
$var reg 1 # decide $end
$var reg 24 $ in [23:0] $end
$var reg 1 % reset $end
$var reg 1 & sclk $end
$var reg 1 ' sdio_reg_m $end
$var reg 1 ( sen $end
$var integer 32 ) i [31:0] $end
$scope module S1 $end
$var wire 1 % reset $end
$var wire 1 & sclk $end
$var wire 1 ! sdio $end
$var wire 1 ( sen $end
$var parameter 2 * NO $end
$var parameter 2 + READ $end
$var parameter 2 , WRITE $end
$var reg 12 - address [11:0] $end
$var reg 4 . address_count [3:0] $end
$var reg 24 / bit_24_reg [23:0] $end
$var reg 5 0 bit_counter [4:0] $end
$var reg 8 1 data [7:0] $end
$var reg 3 2 data_count_r [2:0] $end
$var reg 3 3 data_count_w [2:0] $end
$var reg 1 4 read_write_bit $end
$var reg 1 5 sdio_reg_s $end
$var reg 2 6 state [1:0] $end
$upscope $end
$upscope $end
$enddefinitions $end
$comment Show the parameter values. $end
$dumpall
b10 ,
b1 +
b0 *
$end
#0
$dumpvars
b0 6
05
04
b0 3
b0 2
b0 1
b0 0
b0 /
b0 .
b0 -
b0 )
1(
x'
1&
0%
b10100000110110001100 $
0#
b0 "
x!
$end
#50
1%
0&
#90
0%
#100
1&
#150
0&
#200
b1 0
0!
1&
0'
0(
#250
0&
#300
b10 0
1&
b1 )
#350
0&
#400
b11 0
1&
b10 )
#450
0&
#500
b100 0
1&
b11 )
#550
0&
#600
b100000000000 -
b1 .
b10000000000000000000 /
b101 0
1!
1&
1'
b100 )
#650
0&
#700
b10 .
b110 0
0!
1&
0'
b101 )
#750
0&
#800
b101000000000 -
b11 .
b10100000000000000000 /
b111 0
1!
1&
1'
b110 )
#850
0&
#900
b100 .
b1000 0
0!
1&
0'
b111 )
#950
0&
#1000
b101 .
b1001 0
1&
b1000 )
#1050
0&
#1100
b110 .
b1010 0
1&
b1001 )
#1150
0&
#1200
b111 .
b1011 0
1&
b1010 )
#1250
0&
#1300
b1000 .
b1100 0
1&
b1011 )
#1350
0&
#1400
b101000001000 -
b1001 .
b10100000100000000000 /
b1101 0
1!
1&
1'
b1100 )
#1450
0&
#1500
b101000001100 -
b1010 .
b10100000110000000000 /
b1110 0
1&
b1101 )
#1550
0&
#1600
b1011 .
b1111 0
0!
1&
0'
b1110 )
#1650
0&
#1700
b10 6
b101000001101 -
b1100 .
b10100000110100000000 /
b10000 0
1!
1&
1'
b1111 )
#1750
0&
#1800
b1 3
b10100000110110000000 /
b10001 0
1&
b10000 )
#1850
0&
#1900
b10 3
b10010 0
0!
1&
0'
b10001 )
#1950
0&
#2000
b11 3
b10011 0
1&
b10010 )
#2050
0&
#2100
b100 3
b10100 0
1&
b10011 )
#2150
0&
#2200
b101 3
b10100000110110001000 /
b10101 0
1!
1&
1'
b10100 )
#2250
0&
#2300
b110 3
b10100000110110001100 /
b10110 0
1&
b10101 )
#2350
0&
#2400
b111 3
b10111 0
0!
1&
0'
b10110 )
#2450
0&
#2500
b0 3
b11000 0
1&
b10111 )
#2550
0&
#2600
b0 6
b0 .
b0 0
b0 /
b0 -
1&
1(
b11000 )
